p_token_query/__init__.py
p_token_query/config/__init__.py
p_token_query/config/global_config.py
p_token_query/contract/__init__.py
p_token_query/contract/bep20_contract.py
p_token_query/query/__init__.py
p_token_query/query/bep20_query.py
PTokenQuery-0.0.3.dist-info/LICENSE
PTokenQuery-0.0.3.dist-info/METADATA
PTokenQuery-0.0.3.dist-info/WHEEL
PTokenQuery-0.0.3.dist-info/top_level.txt
PTokenQuery-0.0.3.dist-info/RECORD
